gfwlist2privoxy/__init__.py
gfwlist2privoxy/main.py
gfwlist2privoxy/resources/__init__.py
gfwlist2privoxy/resources/builtin.txt
gfwlist2privoxy/resources/gfwlist.action
gfwlist2privoxy/resources/tld.txt
py3_gfwlist2privoxy-1.0.0.dist-info/LICENSE
py3_gfwlist2privoxy-1.0.0.dist-info/METADATA
py3_gfwlist2privoxy-1.0.0.dist-info/WHEEL
py3_gfwlist2privoxy-1.0.0.dist-info/entry_points.txt
py3_gfwlist2privoxy-1.0.0.dist-info/top_level.txt
py3_gfwlist2privoxy-1.0.0.dist-info/RECORD
