Metadata-Version: 2.1
Name: py3-gfwlist2privoxy
Version: 1.0.0
Summary: convert gfwlist to privoxy action file
Home-page: https://github.com/CoCongV/gfwlist2privoxy
Author: CoCong
Author-email: cong.lv.yx@gmail.com
License: MIT
Platform: UNKNOWN
Classifier: License :: OSI Approved :: MIT License
Classifier: Programming Language :: Python :: 3.7
